{
  "enabled": true,
  "adProvider": "adsense",
  "adsensePublisherId": "",
  "adsenseSlotId": "",
  "adDurationSeconds": 5,
  "renewMode": "ad-required",
  "showAdOnExpired": true,
  "showAdOnEarlyRenew": true,
  "skipAllowed": false,
  "skipAfterSeconds": 3,
  "customAdHtml": "",
  "rewardOnComplete": false,
  "rewardType": "bluecoin",
  "rewardAmount": 100,
  "bannerAdEnabled": false,
  "bannerAdHtml": "",
  "estimatedRpm": 2.5,
  "pageAds": {
    "home": false,
    "rankings": false,
    "mining": false,
    "exchange": false,
    "shop": false,
    "tournament": false
  },
  "stats": {
    "totalImpressions": 0,
    "totalCompletions": 0,
    "totalSkips": 0,
    "estimatedRevenue": 0,
    "lastReset": null
  }
}