{
  "startedAt": 1753266000000,
  "peakConcurrentEver": 7,
  "dailyStats": {
    "2026-07-23": {
      "pageViews": 131,
      "uniqueSessions": 37,
      "pages": {
        "/": 73,
        "/mining": 15,
        "/tournament": 5,
        "/rankings": 11,
        "/exchange": 10,
        "/shop": 17
      },
      "referrers": {
        "Referral": 58,
        "Direct": 73
      },
      "devices": {
        "Desktop": 131
      },
      "browsers": {
        "Firefox": 108,
        "Chrome": 23
      },
      "os": {
        "Linux": 131
      },
      "peakConcurrent": 7
    }
  }
}